AUTHORS
CONTRIBUTING.md
LICENSE
MANIFEST.in
PLAN
README.md
setup.py
django_twitter_bootstrap.egg-info/PKG-INFO
django_twitter_bootstrap.egg-info/SOURCES.txt
django_twitter_bootstrap.egg-info/dependency_links.txt
django_twitter_bootstrap.egg-info/top_level.txt
twitter_bootstrap/__init__.py
twitter_bootstrap/models.py
twitter_bootstrap/static/js/affix.js
twitter_bootstrap/static/js/alert.js
twitter_bootstrap/static/js/button.js
twitter_bootstrap/static/js/carousel.js
twitter_bootstrap/static/js/collapse.js
twitter_bootstrap/static/js/dropdown.js
twitter_bootstrap/static/js/modal.js
twitter_bootstrap/static/js/popover.js
twitter_bootstrap/static/js/scrollspy.js
twitter_bootstrap/static/js/tab.js
twitter_bootstrap/static/js/tooltip.js
twitter_bootstrap/static/js/transition.js
twitter_bootstrap/static/less/alerts.less
twitter_bootstrap/static/less/badges.less
twitter_bootstrap/static/less/bootstrap.less
twitter_bootstrap/static/less/breadcrumbs.less
twitter_bootstrap/static/less/button-groups.less
twitter_bootstrap/static/less/buttons.less
twitter_bootstrap/static/less/carousel.less
twitter_bootstrap/static/less/close.less
twitter_bootstrap/static/less/code.less
twitter_bootstrap/static/less/component-animations.less
twitter_bootstrap/static/less/dropdowns.less
twitter_bootstrap/static/less/forms.less
twitter_bootstrap/static/less/grid.less
twitter_bootstrap/static/less/input-groups.less
twitter_bootstrap/static/less/jumbotron.less
twitter_bootstrap/static/less/labels.less
twitter_bootstrap/static/less/list-group.less
twitter_bootstrap/static/less/media.less
twitter_bootstrap/static/less/mixins.less
twitter_bootstrap/static/less/modals.less
twitter_bootstrap/static/less/navbar.less
twitter_bootstrap/static/less/navs.less
twitter_bootstrap/static/less/normalize.less
twitter_bootstrap/static/less/pager.less
twitter_bootstrap/static/less/pagination.less
twitter_bootstrap/static/less/panels.less
twitter_bootstrap/static/less/popovers.less
twitter_bootstrap/static/less/print.less
twitter_bootstrap/static/less/progress-bars.less
twitter_bootstrap/static/less/responsive-utilities.less
twitter_bootstrap/static/less/scaffolding.less
