Metadata-Version: 1.0
Name: django-twitter-bootstrap
Version: 3.0.0-rc2
Summary: Provides a Django app whose static folder contains Twitter Bootstrap assets
Home-page: https://github.com/estebistec/django-twitter-bootstrap
Author: Steven Cummings
Author-email: cummingscs@gmail.com
License: MIT
Download-URL: http://pypi.python.org/pypi/django-twitter-bootstrap
Keywords: django app staticfiles twitter bootstrap
Platform: UNKNOWN
Classifier: Development Status :: 4 - Beta
Classifier: Environment :: Web Environment
Classifier: Framework :: Django
Classifier: Intended Audience :: Developers
Classifier: License :: OSI Approved :: MIT License
Classifier: Programming Language :: Python
Classifier: Programming Language :: Python :: 2.7
Classifier: Topic :: Software Development :: Libraries
